{"L-1": 1, "L-2": 2, "L-3": 3, "L-4": 4, "L-5": 5, "L0": 6, "L1": 7, "L10": 8, "L11": 9, "L2": 10, "L3": 11, "L4": 12, "L5": 13, "L6": 14, "L7": 15, "L8": 16, "L9": 17, "S-1": 18, "S-2": 19, "S-3": 20, "S-4": 21, "S-5": 22, "S0": 23, "S1": 24, "S10": 25, "S11": 26, "S2": 27, "S3": 28, "S4": 29, "S5": 30, "S6": 31, "S7": 32, "S8": 33, "S9": 34, "accidental.double_flat": 35, "accidental.flat": 36, "accidental.natural": 37, "accidental.sharp": 38, "clef.C": 39, "clef.Fpetrucci": 40, "clef.G": 41, "clef.G_8vb": 42, "custos": 43, "digit.2": 44, "digit.3": 45, "digit.8": 46, "dot": 47, "lnote.breve": 48, "lnote.oblique": 49, "metersign.Ccut": 50, "metersign.Ct": 51, "metersign.O": 52, "metersign.Ocut": 53, "metersign.Odot": 54, "note.breve": 55, "note.eighthCut_up": 56, "note.eighth_down": 57, "note.eighth_up": 58, "note.half_down": 59, "note.half_up": 60, "note.longa2_down": 61, "note.quarter": 62, "note.quarter_down": 63, "note.quarter_up": 64, "note.whole": 65, "rest.breve": 66, "rest.half": 67, "rest.longa2": 68, "rest.seminima": 69, "rest.whole": 70, "verticalLine": 71, "<PAD>": 0}